{
  "resourceType": "StructureDefinition",
  "id": "types-of-violence",
  "url": "http://fhir.org/guides/who/anc-cds/StructureDefinition/types-of-violence",
  "name": "Types of violence",
  "title": "Types of violence",
  "status": "draft",
  "experimental": false,
  "description": "What type(s) of violence has the client been subjected to?",
  "fhirVersion": "4.0.1",
  "kind": "resource",
  "abstract": false,
  "type": "Observation",
  "baseDefinition": "http://hl7.org/fhir/StructureDefinition/Observation",
  "derivation": "constraint",
  "differential": {
    "element": [ {
      "id": "Observation",
      "path": "Observation",
      "short": "Types of violence",
      "comment": "Strengthening health systems to respond to women subjected to intimate partner violence or sexual violence: a manual for health managers (2017) (5)",
      "mustSupport": false
    }, {
      "id": "Observation.valueCodeableConcept",
      "path": "Observation.valueCodeableConcept",
      "min": 0,
      "max": "*",
      "type": [ {
        "code": "CodeableConcept"
      } ],
      "mustSupport": true,
      "binding": {
        "strength": "extensible",
        "valueSet": "http://fhir.org/guides/who/anc-cds/ValueSet/types-of-violence-values"
      }
    } ]
  }
}