{
  "resourceType": "ValueSet",
  "id": "persistent-physiological-symptoms-breathless-during-routine-activities-choices",
  "url": "http://fhir.org/guides/who/anc-cds/ValueSet/persistent-physiological-symptoms-breathless-during-routine-activities-choices",
  "name": "persistent-physiological-symptoms-breathless-during-routine-activities-choices",
  "title": "Persistent physiological symptoms - Breathless during routine activities Choices",
  "status": "draft",
  "experimental": false,
  "description": "Codes representing possible values for the Persistent physiological symptoms - Breathless during routine activities Choices element",
  "immutable": true,
  "compose": {
    "include": [ {
      "system": "http://hl7.org/fhir/sid/icd-10",
      "concept": [ {
        "code": "R06.0",
        "display": "Dyspnoea"
      } ]
    }, {
      "system": "http://snomed.info/sct",
      "concept": [ {
        "code": "267036007",
        "display": "Dyspnea (finding)"
      } ]
    }, {
      "system": "http://loinc.org",
      "concept": [ {
        "code": "45705-1",
        "display": "Shortness of breath [Minimum Data Set]??Note: Multiple options on LOINC"
      } ]
    }, {
      "system": "http://hl7.org/fhir/sid/icd-11",
      "concept": [ {
        "code": "MD11.5",
        "display": "Dyspnoea"
      } ]
    }, {
      "system": "http://hl7.org/fhir/sid/icf-nl",
      "concept": [ {
        "code": "b460",
        "display": "Sensations associated with cardiovascular and respiratory functions"
      } ]
    } ]
  }
}