{
  "resourceType": "ValueSet",
  "id": "amniotic-fluid-level-choices",
  "url": "http://fhir.org/guides/who/anc-cds/ValueSet/amniotic-fluid-level-choices",
  "name": "amniotic-fluid-level-choices",
  "title": "Amniotic fluid level Choices",
  "status": "draft",
  "experimental": false,
  "description": "Codes representing possible values for the Amniotic fluid level Choices element",
  "immutable": true,
  "compose": {
    "include": [ {
      "system": "http://fhir.org/guides/who/anc-cds/CodeSystem/anc-custom",
      "concept": [ {
        "code": "Amniotic fluid level-Normal amniotic fluid level",
        "display": "Normal amniotic fluid level"
      }, {
        "code": "Amniotic fluid level-Reduced amniotic fluid level",
        "display": "Reduced amniotic fluid level"
      }, {
        "code": "Amniotic fluid level-Increased amniotic fluid level",
        "display": "Increased amniotic fluid level"
      } ]
    } ]
  }
}