{
  "resourceType": "ValueSet",
  "id": "anc-b6-de73",
  "url": "http://fhir.org/guides/who/anc-cds/ValueSet/anc-b6-de73",
  "name": "PastsurgeriesChoices",
  "title": "Past surgeries Choices",
  "status": "draft",
  "experimental": false,
  "description": "Codes representing possible values for the Past surgeries Choices element",
  "immutable": true,
  "compose": {
    "include": [ {
      "system": "http://fhir.org/guides/who/anc-cds/CodeSystem/anc-custom-codes",
      "concept": [ {
        "code": "ANC.B6.DE73",
        "display": "No known past surgeries"
      }, {
        "code": "ANC.B6.DE74",
        "display": "Does not know of any past surgeries"
      }, {
        "code": "ANC.B6.DE75",
        "display": "Dilation and curettage"
      }, {
        "code": "ANC.B6.DE76",
        "display": "Myomectomy"
      }, {
        "code": "ANC.B6.DE77",
        "display": "Removal of ovarian cysts"
      }, {
        "code": "ANC.B6.DE78",
        "display": "Oophorectomy"
      }, {
        "code": "ANC.B6.DE79",
        "display": "Salpingectomy"
      }, {
        "code": "ANC.B6.DE80",
        "display": "Cervical cone"
      }, {
        "code": "ANC.B6.DE81",
        "display": "Other gynecological procedures (specify)"
      }, {
        "code": "ANC.B6.DE82",
        "display": "Other surgeries (specify)"
      } ]
    } ]
  }
}