{
  "resourceType": "ValueSet",
  "id": "emergency-referral",
  "url": "http://fhir.org/guides/who/anc-cds/ValueSet/emergency-referral",
  "name": "emergency-referral",
  "title": "Emergency referral",
  "status": "draft",
  "experimental": false,
  "description": "Codes representing possible values for the Emergency referral element",
  "immutable": true,
  "compose": {
    "include": [ {
      "system": "http://snomed.info/sct",
      "concept": [ {
        "code": "183866009",
        "display": "Referral to emergency clinic (procedure)"
      } ]
    }, {
      "system": "http://loinc.org",
      "concept": [ {
        "code": "39269-6"
      } ]
    }, {
      "system": "https://mitel.dimi.uniud.it/ichi/#http://id.who.int/ichi",
      "concept": [ {
        "code": "UEP.TI.ZZ",
        "display": "Referral to health provider"
      } ]
    } ]
  }
}