{
  "resourceType": "ValueSet",
  "id": "current-physiological-symptoms-choices",
  "url": "http://fhir.org/guides/who/anc-cds/ValueSet/current-physiological-symptoms-choices",
  "name": "current-physiological-symptoms-choices",
  "title": "Current physiological symptoms-choices",
  "status": "draft",
  "experimental": false,
  "description": "Codes representing possible values for the Current physiological symptoms-choices element",
  "immutable": true,
  "compose": {
    "include": [ {
      "system": "http://snomed.info/sct",
      "concept": [ {
        "code": "161915001",
        "display": "Current physiological symptoms"
      }, {
        "code": "111972009",
        "display": "Current physiological symptoms"
      }, {
        "code": "289567003",
        "display": "Current physiological symptoms"
      }, {
        "code": "267036007",
        "display": "Current physiological symptoms"
      }, {
        "code": "14760008",
        "display": "Current physiological symptoms"
      }, {
        "code": "249123005",
        "display": "Current physiological symptoms"
      }, {
        "code": "49727002",
        "display": "Current physiological symptoms"
      }, {
        "code": "386661006",
        "display": "Current physiological symptoms"
      }, {
        "code": "84229001",
        "display": "Current physiological symptoms"
      }, {
        "code": "25064002",
        "display": "Current physiological symptoms"
      }, {
        "code": "16331000",
        "display": "Current physiological symptoms"
      }, {
        "code": "1.56399E+16",
        "display": "Current physiological symptoms"
      }, {
        "code": "420356000",
        "display": "Current physiological symptoms"
      }, {
        "code": "422587007",
        "display": "Current physiological symptoms"
      }, {
        "code": "267038008",
        "display": "Current physiological symptoms"
      }, {
        "code": "49650001",
        "display": "Current physiological symptoms"
      }, {
        "code": "1.22475E+16",
        "display": "Current physiological symptoms"
      }, {
        "code": "279039007",
        "display": "Current physiological symptoms"
      }, {
        "code": "274671002",
        "display": "Current physiological symptoms"
      }, {
        "code": "703619001",
        "display": "Current physiological symptoms"
      }, {
        "code": "22253000",
        "display": "Current physiological symptoms"
      }, {
        "code": "289530006",
        "display": "Current physiological symptoms"
      }, {
        "code": "128060009",
        "display": "Current physiological symptoms"
      }, {
        "code": "63102001",
        "display": "Current physiological symptoms"
      }, {
        "code": "422400008",
        "display": "Current physiological symptoms"
      } ]
    }, {
      "system": "http://hl7.org/fhir/sid/icd-10",
      "concept": [ {
        "code": "R00.8",
        "display": "Current physiological symptoms"
      }, {
        "code": "N89.8",
        "display": "Current physiological symptoms"
      }, {
        "code": "R06.0",
        "display": "Current physiological symptoms"
      }, {
        "code": "K59.0",
        "display": "Current physiological symptoms"
      }, {
        "code": "O75.9",
        "display": "Current physiological symptoms"
      }, {
        "code": "R05",
        "display": "Current physiological symptoms"
      }, {
        "code": "R50.9",
        "display": "Current physiological symptoms"
      }, {
        "code": "R53",
        "display": "Current physiological symptoms"
      }, {
        "code": "R51",
        "display": "Current physiological symptoms"
      }, {
        "code": "R12",
        "display": "Current physiological symptoms"
      }, {
        "code": "R25.2",
        "display": "Current physiological symptoms"
      }, {
        "code": "L53.9",
        "display": "Current physiological symptoms"
      }, {
        "code": "R11",
        "display": "Current physiological symptoms"
      }, {
        "code": "R60.0",
        "display": "Current physiological symptoms"
      }, {
        "code": "R30.0",
        "display": "Current physiological symptoms"
      }, {
        "code": "M79.6",
        "display": "Current physiological symptoms"
      }, {
        "code": "M54.5",
        "display": "Current physiological symptoms"
      }, {
        "code": "R10.2",
        "display": "Current physiological symptoms"
      }, {
        "code": "O71.6",
        "display": "Current physiological symptoms"
      }, {
        "code": "R52.9",
        "display": "Current physiological symptoms"
      }, {
        "code": "O46.9",
        "display": "Current physiological symptoms"
      }, {
        "code": "I83.9",
        "display": "Current physiological symptoms"
      }, {
        "code": "H53.9",
        "display": "Current physiological symptoms"
      } ]
    }, {
      "system": "http://loinc.org",
      "concept": [ {
        "code": "8884-9",
        "display": "Current physiological symptoms"
      }, {
        "code": "70380-1",
        "display": "Current physiological symptoms"
      }, {
        "code": "45705-1",
        "display": "Current physiological symptoms"
      }, {
        "code": "28235-0",
        "display": "Current physiological symptoms"
      }, {
        "code": "56866-7",
        "display": "Current physiological symptoms"
      }, {
        "code": "64439-3",
        "display": "Current physiological symptoms"
      }, {
        "code": "45701-0",
        "display": "Current physiological symptoms"
      }, {
        "code": "70304-1",
        "display": "Current physiological symptoms"
      }, {
        "code": "45715-0",
        "display": "Current physiological symptoms"
      }, {
        "code": "70387-6",
        "display": "Current physiological symptoms"
      }, {
        "code": "70628-3",
        "display": "Current physiological symptoms"
      }, {
        "code": "66530-7",
        "display": "Current physiological symptoms"
      }, {
        "code": "42848-2",
        "display": "Current physiological symptoms"
      }, {
        "code": "45700-2",
        "display": "Current physiological symptoms"
      }, {
        "code": "45721-8",
        "display": "Current physiological symptoms"
      }, {
        "code": "45712-7",
        "display": "Current physiological symptoms"
      }, {
        "code": "70842-0",
        "display": "Current physiological symptoms"
      }, {
        "code": "70360-3",
        "display": "Current physiological symptoms"
      }, {
        "code": "65727-0",
        "display": "Current physiological symptoms"
      }, {
        "code": "45708-5",
        "display": "Current physiological symptoms"
      } ]
    }, {
      "system": "http://hl7.org/fhir/sid/icd-11",
      "concept": [ {
        "code": "MC81.Z",
        "display": "Current physiological symptoms"
      }, {
        "code": "MF3A",
        "display": "Current physiological symptoms"
      }, {
        "code": "MD11.5",
        "display": "Current physiological symptoms"
      }, {
        "code": "ME05.0",
        "display": "Current physiological symptoms"
      }, {
        "code": "JA8D.Z",
        "display": "Current physiological symptoms"
      }, {
        "code": "MD12",
        "display": "Current physiological symptoms"
      }, {
        "code": "MG26",
        "display": "Current physiological symptoms"
      }, {
        "code": "MB22.7",
        "display": "Current physiological symptoms"
      }, {
        "code": "MG31.1",
        "display": "Current physiological symptoms"
      }, {
        "code": "MD95",
        "display": "Current physiological symptoms"
      }, {
        "code": "MB47.3",
        "display": "Current physiological symptoms"
      }, {
        "code": "ME64.0",
        "display": "Current physiological symptoms"
      }, {
        "code": "MD90.0 Nausea",
        "display": "Current physiological symptoms"
      }, {
        "code": "MG29.0Y",
        "display": "Current physiological symptoms"
      }, {
        "code": "MF50.7",
        "display": "Current physiological symptoms"
      }, {
        "code": "FB56.4",
        "display": "Current physiological symptoms"
      }, {
        "code": "ME84.2Z",
        "display": "Current physiological symptoms"
      }, {
        "code": "MD81.11",
        "display": "Current physiological symptoms"
      }, {
        "code": "JA65.7",
        "display": "Current physiological symptoms"
      }, {
        "code": "MG3Z",
        "display": "Current physiological symptoms"
      }, {
        "code": "JA41.Z",
        "display": "Current physiological symptoms"
      }, {
        "code": "BD74.1Z",
        "display": "Current physiological symptoms"
      }, {
        "code": "MC1Y",
        "display": "Current physiological symptoms"
      }, {
        "code": "MD90.1",
        "display": "Current physiological symptoms"
      } ]
    }, {
      "system": "http://hl7.org/fhir/sid/icf-nl",
      "concept": [ {
        "code": "s63033",
        "display": "Current physiological symptoms"
      }, {
        "code": "b460",
        "display": "Current physiological symptoms"
      }, {
        "code": "b525",
        "display": "Current physiological symptoms"
      }, {
        "code": "b28012",
        "display": "Current physiological symptoms"
      }, {
        "code": "b450",
        "display": "Current physiological symptoms"
      }, {
        "code": "b4552",
        "display": "Current physiological symptoms"
      }, {
        "code": "b535",
        "display": "Current physiological symptoms"
      }, {
        "code": "b5350",
        "display": "Current physiological symptoms"
      }, {
        "code": "b28013",
        "display": "Current physiological symptoms"
      }, {
        "code": "b2800",
        "display": "Current physiological symptoms"
      }, {
        "code": "b4152",
        "display": "Current physiological symptoms"
      }, {
        "code": "b21009",
        "display": "Current physiological symptoms"
      }, {
        "code": "b5106",
        "display": "Current physiological symptoms"
      } ]
    }, {
      "system": "http://fhir.org/guides/who/anc-cds/CodeSystem/anc-custom",
      "concept": [ {
        "code": "Current physiological symptoms",
        "display": "Current physiological symptoms"
      } ]
    } ]
  }
}