{
  "resourceType": "ValueSet",
  "id": "anc-end-26",
  "url": "http://fhir.org/guides/who/anc-cds/ValueSet/anc-end-26",
  "name": "DeliverycomplicationsChoices",
  "title": "Delivery complications Choices",
  "status": "draft",
  "experimental": false,
  "description": "Codes representing possible values for the Delivery complications Choices element",
  "immutable": true,
  "compose": {
    "include": [ {
      "system": "http://fhir.org/guides/who/anc-cds/CodeSystem/anc-custom-codes",
      "concept": [ {
        "code": "ANC.End.26",
        "display": "No complications"
      }, {
        "code": "ANC.End.27",
        "display": "Postpartum haemorrhage"
      }, {
        "code": "ANC.End.28",
        "display": "Antepartum haemorrhage"
      }, {
        "code": "ANC.End.29",
        "display": "Placenta praevia"
      }, {
        "code": "ANC.End.30",
        "display": "Placental abruption"
      }, {
        "code": "ANC.End.31",
        "display": "Cord prolapse"
      }, {
        "code": "ANC.End.32",
        "display": "Obstructed labour"
      }, {
        "code": "ANC.End.33",
        "display": "Abnormal presentation"
      }, {
        "code": "ANC.End.34",
        "display": "Pre-eclampsia"
      }, {
        "code": "ANC.End.35",
        "display": "Eclampsia"
      }, {
        "code": "ANC.End.36",
        "display": "Perineal tear (3rd, or 4th degree)"
      }, {
        "code": "ANC.End.37",
        "display": "Other (specify)"
      } ]
    } ]
  }
}