{
  "resourceType": "ValueSet",
  "id": "co-habitants",
  "url": "http://fhir.org/guides/who/anc-cds/ValueSet/co-habitants",
  "name": "co-habitants",
  "title": "Co-habitants",
  "status": "draft",
  "experimental": false,
  "description": "Codes representing possible values for the Co-habitants element",
  "immutable": true,
  "compose": {
    "include": [ {
      "system": "http://fhir.org/guides/who/anc-cds/CodeSystem/anc-custom",
      "concept": [ {
        "code": "Co-habitants",
        "display": "Co-habitants"
      } ]
    } ]
  }
}