{
  "resourceType": "ValueSet",
  "id": "second-body-temperature",
  "url": "http://fhir.org/guides/who/anc-cds/ValueSet/second-body-temperature",
  "name": "second-body-temperature",
  "title": "Second body temperature",
  "status": "draft",
  "experimental": false,
  "description": "Codes representing possible values for the Second body temperature element",
  "immutable": true,
  "compose": {
    "include": [ {
      "system": "http://snomed.info/sct",
      "concept": [ {
        "code": "386725007",
        "display": "Second body temperature"
      } ]
    }, {
      "system": "http://loinc.org",
      "concept": [ {
        "code": "8310-5",
        "display": "Second body temperature"
      } ]
    }, {
      "system": "http://hl7.org/fhir/sid/icf-nl",
      "concept": [ {
        "code": "b5500",
        "display": "Second body temperature"
      } ]
    } ]
  }
}