{
  "resourceType": "ValueSet",
  "id": "anc-b10-de171",
  "url": "http://fhir.org/guides/who/anc-cds/ValueSet/anc-b10-de171",
  "name": "TetanustoxoidTT4immunizationprovided",
  "title": "Tetanus toxoid (TT) 4 immunization provided",
  "status": "draft",
  "experimental": false,
  "description": "Codes representing possible values for the Tetanus toxoid (TT) 4 immunization provided element",
  "immutable": true,
  "compose": {
    "include": [ {
      "system": "http://fhir.org/guides/who/anc-cds/CodeSystem/anc-custom-codes",
      "concept": [ {
        "code": "ANC.B10.DE171",
        "display": "Tetanus toxoid (TT) 4 immunization provided"
      } ]
    } ]
  }
}