{
  "resourceType": "ValueSet",
  "id": "tetanus-toxoid-tt-1-immunization-provided",
  "url": "http://fhir.org/guides/who/anc-cds/ValueSet/tetanus-toxoid-tt-1-immunization-provided",
  "name": "tetanus-toxoid-tt-1-immunization-provided",
  "title": "Tetanus toxoid (TT) 1 immunization provided",
  "status": "draft",
  "experimental": false,
  "description": "Codes representing possible values for the Tetanus toxoid (TT) 1 immunization provided element",
  "immutable": true,
  "compose": {
    "include": [ {
      "system": "http://hl7.org/fhir/sid/icd-10",
      "concept": [ {
        "code": "Z23.5",
        "display": "Need for immunization against tetanus alone"
      } ]
    }, {
      "system": "http://snomed.info/sct",
      "concept": [ {
        "code": "170330007",
        "display": "Administration of first dose of vaccine product containing only Clostridium tetani antigen (procedure)"
      } ]
    }, {
      "system": "http://hl7.org/fhir/sid/icd-11",
      "concept": [ {
        "code": "QC00.5",
        "display": "Need for immunization against tetanus alone"
      } ]
    }, {
      "system": "https://mitel.dimi.uniud.it/ichi/#http://id.who.int/ichi",
      "concept": [ {
        "code": "DTB.DB.AE",
        "display": "Percutaneous administration of immunological agent, not elsewhere classified"
      } ]
    } ]
  }
}