{
  "resourceType": "ValueSet",
  "id": "pre-gestational-weight",
  "url": "http://fhir.org/guides/who/anc-cds/ValueSet/pre-gestational-weight",
  "name": "pre-gestational-weight",
  "title": "Pre-gestational weight",
  "status": "draft",
  "experimental": false,
  "description": "Codes representing possible values for the Pre-gestational weight element",
  "immutable": true,
  "compose": {
    "include": [ {
      "system": "http://fhir.org/guides/who/anc-cds/CodeSystem/anc-custom",
      "concept": [ {
        "code": "Pre-gestational weight",
        "display": "Pre-gestational weight"
      } ]
    } ]
  }
}