{
  "resourceType": "ValueSet",
  "id": "preventive-antihelminthic-treatment-provided-choices",
  "url": "http://fhir.org/guides/who/anc-cds/ValueSet/preventive-antihelminthic-treatment-provided-choices",
  "name": "preventive-antihelminthic-treatment-provided-choices",
  "title": "Preventive antihelminthic treatment provided Choices",
  "status": "draft",
  "experimental": false,
  "description": "Codes representing possible values for the Preventive antihelminthic treatment provided Choices element",
  "immutable": true,
  "compose": {
    "include": [ {
      "system": "http://fhir.org/guides/who/anc-cds/CodeSystem/anc-custom",
      "concept": [ {
        "code": "Preventive antihelminthic treatment provided-Single-dose albendazole 400 mg",
        "display": "Single-dose albendazole 400 mg"
      }, {
        "code": "Preventive antihelminthic treatment provided-Single-dose mebendazole 500 mg",
        "display": "Single-dose mebendazole 500 mg"
      }, {
        "code": "Preventive antihelminthic treatment provided-No preventative treatment provided",
        "display": "No preventative treatment provided"
      } ]
    } ]
  }
}