{
  "resourceType": "ValueSet",
  "id": "respiratory-exam-result-rales-choices",
  "url": "http://fhir.org/guides/who/anc-cds/ValueSet/respiratory-exam-result-rales-choices",
  "name": "respiratory-exam-result-rales-choices",
  "title": "Respiratory exam result - Rales Choices",
  "status": "draft",
  "experimental": false,
  "description": "Codes representing possible values for the Respiratory exam result - Rales Choices element",
  "immutable": true,
  "compose": {
    "include": [ {
      "system": "http://fhir.org/guides/who/anc-cds/CodeSystem/anc-custom",
      "concept": [ {
        "code": "Respiratory exam result-Rales",
        "display": "Rales"
      } ]
    } ]
  }
}