{
  "resourceType": "CodeSystem",
  "id": "hbsag-dbs-codes",
  "url": "http://fhir.org/guides/who/anc-cds/CodeSystem/hbsag-dbs-codes",
  "name": "hbsag_dbs_codes",
  "title": "Dried Blood Spot (DBS) HBsAg test codes",
  "status": "draft",
  "experimental": false,
  "description": "Codes representing possible values for the Dried Blood Spot (DBS) HBsAg test element",
  "caseSensitive": true,
  "valueSet": "http://fhir.org/guides/who/anc-cds/ValueSet/hbsag-dbs-values",
  "content": "complete",
  "concept": [
    {
      "code": "703AAAAAAAAAAAAAAAAAAAAAAAAAAAAAAAAA",
      "display": "Positive"
    },
    {
      "code": "664AAAAAAAAAAAAAAAAAAAAAAAAAAAAAAAAA",
      "display": "Negative"
    }
  ]
}