{
  "resourceType": "ValueSet",
  "id": "hiv-prep-values",
  "url": "http://fhir.org/guides/who/anc-cds/ValueSet/hiv-prep-values",
  "name": "hiv_prep_values",
  "title": "PrEP for HIV prevention counseling values",
  "status": "draft",
  "experimental": false,
  "description": "Codes representing possible values for the PrEP for HIV prevention counseling element",
  "immutable": true,
  "compose": {
    "include": [
      {
        "system": "http://fhir.org/guides/who/anc-cds/CodeSystem/hiv-prep-codes"
      }
    ]
  }
}