{
  "resourceType": "Observation",
  "id": "anc-b9-de77-example",
  "meta": {
    "profile": [ "http://fhir.org/guides/who/anc-cds/StructureDefinition/anc-b9-de77" ]
  },
  "identifier": [ {
    "use": "official",
    "system": "http://example.org/fhir/NamingSystem/identifiers",
    "value": "anc-b9-de77-example"
  } ],
  "status": "final",
  "code": {
    "coding": [ {
      "system": "http://fhir.org/guides/who/anc-cds/CodeSystem/anc-custom-codes",
      "code": "ANC.B9.DE77",
      "display": "Hepatitis C test required"
    }, {
      "system": "http://snomed.info/sct",
      "code": "413672003",
      "display": "Blood test requested (situation)"
    } ]
  },
  "subject": {
    "reference": "Patient/anc-patient-example"
  },
  "encounter": {
    "reference": "Encounter/anc-encounter-example"
  },
  "performer": [ {
    "reference": "PractitionerRole/anc-practitionerrole-example"
  } ],
  "valueBoolean": true
}